streamlit_plotly_events/__init__.py
streamlit_plotly_events/frontend/.env
streamlit_plotly_events/frontend/.prettierrc
streamlit_plotly_events/frontend/build/asset-manifest.json
streamlit_plotly_events/frontend/build/index.html
streamlit_plotly_events/frontend/build/precache-manifest.e3df0e84b856a278b39da3a085481f45.js
streamlit_plotly_events/frontend/build/service-worker.js
streamlit_plotly_events/frontend/build/static/js/2.a9de1b85.chunk.js
streamlit_plotly_events/frontend/build/static/js/2.a9de1b85.chunk.js.LICENSE.txt
streamlit_plotly_events/frontend/build/static/js/2.a9de1b85.chunk.js.map
streamlit_plotly_events/frontend/build/static/js/main.2ba31fb4.chunk.js
streamlit_plotly_events/frontend/build/static/js/main.2ba31fb4.chunk.js.map
streamlit_plotly_events/frontend/build/static/js/runtime-main.11ec9aca.js
streamlit_plotly_events/frontend/build/static/js/runtime-main.11ec9aca.js.map
streamlit_plotly_events/frontend/package.json
streamlit_plotly_events/frontend/public/index.html
streamlit_plotly_events/frontend/src/StreamlitPlotlyEventsComponent.tsx
streamlit_plotly_events/frontend/src/index.tsx
streamlit_plotly_events/frontend/src/react-app-env.d.ts
streamlit_plotly_events/frontend/tsconfig.json
xt_st_common/__init__.py
xt_st_common/components.py
xt_st_common/config.py
xt_st_common/database.py
xt_st_common/fs_upload_page.py
xt_st_common/project_actions.py
xt_st_common/project_components.py
xt_st_common/project_models.py
xt_st_common/session.py
xt_st_common/storage.py
xt_st_common/utils.py
xt_st_common-1.1.5.dist-info/METADATA
xt_st_common-1.1.5.dist-info/WHEEL
xt_st_common-1.1.5.dist-info/RECORD
